tab_dataset/__init__.py
tab_dataset/cdataset.py
tab_dataset/cfield.py
tab_dataset/dataset.py
tab_dataset/dataset_interface.py
tab_dataset/field.py
tab_dataset/field_interface.py
tab_dataset-0.1.1.dist-info/METADATA
tab_dataset-0.1.1.dist-info/WHEEL
tab_dataset-0.1.1.dist-info/top_level.txt
tab_dataset-0.1.1.dist-info/RECORD
