Metadata-Version: 2.1
Name: tab_dataset
Version: 0.1.1
Summary: TAB-dataset : A tool for structuring tabular data
Home-page: https://github.com/loco-philippe/tab_dataset/blob/main/README.md
Author: Philippe Thomy
Author-email: philippe@loco-labs.io
Keywords: tabular data,open data,environmental data
Classifier: Development Status :: 5 - Production/Stable
Classifier: Intended Audience :: Developers
Classifier: Topic :: Software Development :: Build Tools
Classifier: License :: OSI Approved :: MIT License
Classifier: Programming Language :: Python :: 3
Requires-Python: >=3.9, <4
Requires-Dist: json-ntv
Requires-Dist: tab-analysis
